wink_sdk_extranet_property_register/__init__.py
wink_sdk_extranet_property_register/api_client.py
wink_sdk_extranet_property_register/api_response.py
wink_sdk_extranet_property_register/configuration.py
wink_sdk_extranet_property_register/exceptions.py
wink_sdk_extranet_property_register/py.typed
wink_sdk_extranet_property_register/rest.py
wink_sdk_extranet_property_register/api/__init__.py
wink_sdk_extranet_property_register/api/leads_api.py
wink_sdk_extranet_property_register/api/manage_leads_api.py
wink_sdk_extranet_property_register/api/property_registration_api.py
wink_sdk_extranet_property_register/api/registration_api.py
wink_sdk_extranet_property_register/models/__init__.py
wink_sdk_extranet_property_register/models/address_affiliate.py
wink_sdk_extranet_property_register/models/address_supplier.py
wink_sdk_extranet_property_register/models/aggregate_greendex_answers_supplier.py
wink_sdk_extranet_property_register/models/aggregate_greendex_score_by_category_supplier.py
wink_sdk_extranet_property_register/models/contact_supplier.py
wink_sdk_extranet_property_register/models/count_response_supplier.py
wink_sdk_extranet_property_register/models/country_lightweight_affiliate.py
wink_sdk_extranet_property_register/models/country_lightweight_supplier.py
wink_sdk_extranet_property_register/models/country_supplier.py
wink_sdk_extranet_property_register/models/custom_monetary_amount.py
wink_sdk_extranet_property_register/models/general_manager_supplier.py
wink_sdk_extranet_property_register/models/generic_error_message.py
wink_sdk_extranet_property_register/models/geo_json_point_affiliate.py
wink_sdk_extranet_property_register/models/geo_json_point_supplier.py
wink_sdk_extranet_property_register/models/geo_name_lightweight_affiliate.py
wink_sdk_extranet_property_register/models/geo_name_lightweight_supplier.py
wink_sdk_extranet_property_register/models/geo_name_supplier.py
wink_sdk_extranet_property_register/models/google_place_detail_request_affiliate.py
wink_sdk_extranet_property_register-0.0.57.dist-info/licenses/LICENSE
wink_sdk_extranet_property_register-0.0.57.dist-info/METADATA
wink_sdk_extranet_property_register-0.0.57.dist-info/WHEEL
wink_sdk_extranet_property_register-0.0.57.dist-info/top_level.txt
wink_sdk_extranet_property_register-0.0.57.dist-info/RECORD
